src/dataaugmentationga_ane.martinez/__init__.py
src/dataaugmentationga_ane.martinez/functions.py
dataaugmentationga_anemartinez-0.0.5.dist-info/METADATA
dataaugmentationga_anemartinez-0.0.5.dist-info/WHEEL
dataaugmentationga_anemartinez-0.0.5.dist-info/licenses/LICENSE
dataaugmentationga_anemartinez-0.0.5.dist-info/RECORD
