Metadata-Version: 2.1
Name: dataaugmentationga_anemartinez
Version: 0.0.5
Summary: This is a library that makes data augmentation based on SDV library using a single objective algorithm to get the distributions of the variables.
Project-URL: Homepage, https://github.com/anemartinez1/pypi_project
Project-URL: Bug Tracker, https://github.com/anemartinez1/pypi_project/issues
Author-email: Elene Astondoa and Ane Martínez <anemartinezorellana@outlook.es>
License-File: LICENSE
Classifier: License :: OSI Approved :: MIT License
Classifier: Operating System :: OS Independent
Classifier: Programming Language :: Python :: 3
Requires-Python: >=3.9
